{
  "StSShapeShifter:TortoiseFormStance": {
    "NAME": "Tortoise Form",
    "DESCRIPTIONS": ["Gain 1 Dexterity", "Or more, idk", "salkdna"]
  },
  "StSShapeShifter:LynxFormStance": {
    "NAME": "Lynx Form",
    "DESCRIPTIONS": ["Gain 1 Dexterity", "Or more, idk", "salkdna"]
  },
  "StSShapeShifter:DeerFormStance": {
    "NAME": "Deer Form",
    "DESCRIPTIONS": ["Gain 1 Dexterity", "Or more, idk", "salkdna"]
  },
  "StSShapeShifter:BearFormStance": {
    "NAME": "Bear Form",
    "DESCRIPTIONS": ["Gain 1 Dexterity", "Or more, idk", "salkdna"]
  },
  "StSShapeShifter:DragonFormStance": {
    "NAME": "Dragon Form",
    "DESCRIPTIONS": ["Gain 1 Dexterity", "Or more, idk", "salkdna"]
  }
}